cyb600_lab1/__init__.py
cyb600_lab1/web_app.py
gtk_cyb600_lab1_TimeApp-1.0.0.data/scripts/web_sync.py
gtk_cyb600_lab1_TimeApp-1.0.0.dist-info/LICENSE
gtk_cyb600_lab1_TimeApp-1.0.0.dist-info/METADATA
gtk_cyb600_lab1_TimeApp-1.0.0.dist-info/WHEEL
gtk_cyb600_lab1_TimeApp-1.0.0.dist-info/top_level.txt
gtk_cyb600_lab1_TimeApp-1.0.0.dist-info/RECORD
