Metadata-Version: 2.1
Name: gtk-cyb600-lab1-TimeApp
Version: 1.0.0
Summary: UNKNOWN
Home-page: UNKNOWN
Author: Gregory Kuhn
Author-email: kuhn7@canisius.edu
License: Apache License Version 2.0
Platform: UNKNOWN
License-File: LICENSE
Requires-Dist: Flask
